gundog_client/__init__.py
gundog_client/_cli.py
gundog_client/_version.py
gundog_client/_tui/__init__.py
gundog_client/_tui/_app.py
gundog_client/_tui/_constants.py
gundog_client/_tui/_enums.py
gundog_client/_tui/_help.py
gundog_client/_tui/_theme.py
gundog_client/_tui/app.tcss
gundog_client/_tui/_modals/__init__.py
gundog_client/_tui/_modals/_input.py
gundog_client/_tui/_themes/__init__.py
gundog_client/_tui/_themes/_dracula.py
gundog_client-0.4.1.dist-info/METADATA
gundog_client-0.4.1.dist-info/WHEEL
gundog_client-0.4.1.dist-info/entry_points.txt
gundog_client-0.4.1.dist-info/RECORD
