Metadata-Version: 2.4
Name: gundog-client
Version: 0.4.1
Summary: Lightweight TUI and CLI client for gundog semantic search
Author: ivdi
License-Expression: GPL-3.0-or-later
Classifier: Development Status :: 3 - Alpha
Classifier: Intended Audience :: Developers
Classifier: License :: OSI Approved :: GNU General Public License v3 or later (GPLv3+)
Classifier: Programming Language :: Python :: 3
Classifier: Programming Language :: Python :: 3.12
Classifier: Programming Language :: Python :: 3.13
Requires-Python: >=3.12
Requires-Dist: gundog-core>=0.3.1
Requires-Dist: rich>=13.0
Requires-Dist: tenacity>=8.0
Requires-Dist: textual>=0.50.0
Requires-Dist: typer>=0.12.0
